{
  "id": 9,
  "name": "Arrow Train",
  "difficulty": "easy",
  "rows": 4,
  "cols": 8,
  "hearts": 3,
  "arrows": [
    {
      "id": "a1",
      "path": [
        [
          1,
          4
        ],
        [
          1,
          5
        ],
        [
          1,
          6
        ]
      ],
      "direction": "R",
      "colorIndex": 0
    },
    {
      "id": "a2",
      "path": [
        [
          1,
          0
        ],
        [
          2,
          0
        ],
        [
          2,
          1
        ],
        [
          2,
          2
        ]
      ],
      "direction": "R",
      "colorIndex": 1
    },
    {
      "id": "a3",
      "path": [
        [
          0,
          5
        ],
        [
          0,
          6
        ]
      ],
      "direction": "R",
      "colorIndex": 2
    },
    {
      "id": "a4",
      "path": [
        [
          0,
          4
        ],
        [
          0,
          3
        ]
      ],
      "direction": "L",
      "colorIndex": 3
    }
  ]
}