{"id":178,"name":"T-Rex 160","difficulty":"easy","rows":32,"cols":30,"hearts":3,"arrows":[{"id":"a1","path":[[20,6],[21,6],[22,6],[22,5],[23,5],[23,6],[23,7],[24,7]],"direction":"D","colorIndex":0},{"id":"a2","path":[[24,10],[25,10],[25,11],[26,11],[26,10],[27,10],[27,11],[28,11]],"direction":"D","colorIndex":1},{"id":"a3","path":[[21,4],[20,4],[20,3],[19,3],[19,2],[20,2],[20,1],[21,1]],"direction":"D","colorIndex":2},{"id":"a4","path":[[24,12],[25,12],[25,13],[26,13],[26,14],[25,14],[25,15],[25,16]],"direction":"R","colorIndex":3},{"id":"a5","path":[[14,15],[14,16],[15,16],[15,15],[16,15],[16,16],[17,16],[17,17]],"direction":"R","colorIndex":4},{"id":"a6","path":[[6,22],[5,22],[5,21],[6,21],[6,20],[5,20],[5,19],[4,19]],"direction":"U","colorIndex":5},{"id":"a7","path":[[12,13],[12,12],[11,12],[11,13],[10,13],[10,14],[9,14],[9,13]],"direction":"L","colorIndex":0},{"id":"a8","path":[[20,7],[19,7],[19,6],[18,6],[18,5],[19,5],[19,4],[18,4]],"direction":"U","colorIndex":1},{"id":"a9","path":[[24,8],[24,9],[25,9],[25,8],[26,8],[26,9],[27,9],[27,8]],"direction":"L","colorIndex":2},{"id":"a10","path":[[19,19],[20,19],[20,18],[20,17],[21,17],[21,18],[22,18],[22,19]],"direction":"R","colorIndex":3},{"id":"a11","path":[[7,25],[7,26],[6,26],[6,25],[5,25],[5,24],[4,24]],"direction":"U","colorIndex":4},{"id":"a12","path":[[17,19],[18,19],[18,18],[19,18],[19,17],[19,16],[18,16],[18,17]],"direction":"R","colorIndex":5},{"id":"a13","path":[[14,18],[14,19],[14,20],[15,20],[15,19],[16,19],[16,20]],"direction":"R","colorIndex":0},{"id":"a14","path":[[13,22],[13,21],[14,21],[14,22],[14,23],[13,23],[13,24],[14,24]],"direction":"D","colorIndex":1},{"id":"a15","path":[[8,22],[8,23],[7,23],[7,24],[8,24],[8,25],[9,25],[9,26]],"direction":"R","colorIndex":2},{"id":"a16","path":[[17,4],[17,3],[18,3],[18,2],[17,2],[17,1],[18,1],[18,0]],"direction":"L","colorIndex":3},{"id":"a17","path":[[13,5],[13,6],[14,6],[14,5],[15,5],[15,4],[14,4]],"direction":"U","colorIndex":4},{"id":"a18","path":[[4,3],[3,3],[2,3],[1,3],[1,4],[2,4],[2,5],[1,5]],"direction":"U","colorIndex":5},{"id":"a19","path":[[4,1],[3,1],[3,0],[2,0],[2,1],[1,1],[1,0],[0,0]],"direction":"U","colorIndex":0},{"id":"a20","path":[[27,16],[27,15],[28,15],[28,14],[27,14],[27,13],[28,13]],"direction":"D","colorIndex":1},{"id":"a21","path":[[13,9],[13,10],[12,10],[12,9],[11,9],[11,10],[10,10],[10,9]],"direction":"L","colorIndex":2},{"id":"a22","path":[[10,22],[10,23],[9,23],[9,22],[9,21],[8,21],[8,20]],"direction":"L","colorIndex":3},{"id":"a23","path":[[13,8],[14,8],[14,7],[13,7],[12,7],[12,6]],"direction":"L","colorIndex":4},{"id":"a24","path":[[6,17],[6,16],[7,16],[7,15],[6,15]],"direction":"U","colorIndex":5},{"id":"a25","path":[[12,17],[11,17],[10,17],[10,18],[9,18],[9,19],[8,19],[8,18]],"direction":"L","colorIndex":0},{"id":"a26","path":[[3,2],[2,2],[1,2],[0,2],[0,3]],"direction":"R","colorIndex":1},{"id":"a27","path":[[9,15],[9,16],[9,17],[8,17],[8,16],[8,15]],"direction":"L","colorIndex":2},{"id":"a28","path":[[13,20],[12,20],[12,21],[11,21],[11,22]],"direction":"R","colorIndex":3},{"id":"a29","path":[[12,23],[11,23],[11,24],[12,24],[12,25]],"direction":"R","colorIndex":4},{"id":"a30","path":[[10,26],[10,25],[11,25],[11,26],[12,26]],"direction":"D","colorIndex":5},{"id":"a31","path":[[17,20],[18,20],[19,20],[20,20]],"direction":"D","colorIndex":0},{"id":"a32","path":[[16,14],[16,13],[15,13],[14,13],[14,12],[13,12],[13,11],[12,11]],"direction":"U","colorIndex":1},{"id":"a33","path":[[16,7],[16,6],[17,6],[17,5],[16,5],[16,4]],"direction":"L","colorIndex":2},{"id":"a34","path":[[22,17],[22,16],[23,16],[23,17]],"direction":"R","colorIndex":3},{"id":"a35","path":[[7,18],[7,19],[6,19],[6,18],[5,18],[5,17]],"direction":"L","colorIndex":4},{"id":"a36","path":[[23,19],[23,18],[24,18]],"direction":"D","colorIndex":5},{"id":"a37","path":[[7,14],[8,14],[8,13]],"direction":"L","colorIndex":0},{"id":"a38","path":[[15,1],[16,1],[16,0]],"direction":"L","colorIndex":1},{"id":"a39","path":[[12,8],[11,8],[11,7]],"direction":"L","colorIndex":2},{"id":"a40","path":[[4,2],[5,2],[5,1]],"direction":"L","colorIndex":3},{"id":"a41","path":[[6,24],[6,23],[5,23],[4,23]],"direction":"U","colorIndex":4},{"id":"a42","path":[[21,19],[21,20]],"direction":"R","colorIndex":5},{"id":"a43","path":[[19,1],[19,0],[20,0]],"direction":"D","colorIndex":0},{"id":"a44","path":[[26,15],[26,16]],"direction":"R","colorIndex":1},{"id":"a45","path":[[15,2],[15,3],[14,3],[14,2]],"direction":"L","colorIndex":2},{"id":"a46","path":[[4,4],[3,4],[3,5]],"direction":"R","colorIndex":3},{"id":"a47","path":[[28,10],[28,9],[28,8]],"direction":"L","colorIndex":4},{"id":"a48","path":[[11,11],[10,11]],"direction":"U","colorIndex":5}]}